Metadata-Version: 2.1
Name: aas-core3.0rc02-testgen
Version: 0.0.1
Summary: Generate test data based on the meta-model V3.0RC02.
Home-page: https://github.com/aas-core-works/aas-core-codegen
Author: Marko Ristin, Nico Braunisch
Author-email: marko@ristin.ch
License: License :: OSI Approved :: MIT License
Keywords: asset administration shell code generation industry 4.0 industrie i4.0
Platform: UNKNOWN
Classifier: Development Status :: 5 - Production/Stable
Classifier: License :: OSI Approved :: MIT License
Classifier: Programming Language :: Python :: 3.8
Classifier: Programming Language :: Python :: 3.9
Classifier: Programming Language :: Python :: 3.10
Provides-Extra: dev
License-File: LICENSE
